pythonopenscad/LICENSE
pythonopenscad/__init__.py
pythonopenscad/base.py
pythonopenscad/dask_anno.py
pythonopenscad/m3dapi.py
pythonopenscad/modifier.py
pythonopenscad/posc_main.py
pythonopenscad/text_render.py
pythonopenscad/text_render5.py
pythonopenscad/text_utils.py
pythonopenscad/examples/__init__.py
pythonopenscad/examples/gist_generator.py
pythonopenscad/examples/gists_2d/__init__.py
pythonopenscad/examples/gists_2d/circle_example.py
pythonopenscad/examples/gists_2d/polygon_example.py
pythonopenscad/examples/gists_2d/square_example.py
pythonopenscad/examples/gists_2d/text_example.py
pythonopenscad/examples/gists_3d/__init__.py
pythonopenscad/examples/gists_3d/cube_example.py
pythonopenscad/examples/gists_3d/cylinder_example.py
pythonopenscad/examples/gists_3d/polyhedron_example.py
pythonopenscad/examples/gists_3d/sphere_example.py
pythonopenscad/examples/gists_csg/__init__.py
pythonopenscad/examples/gists_csg/difference_functional.py
pythonopenscad/examples/gists_csg/difference_operator.py
pythonopenscad/examples/gists_csg/hull_example.py
pythonopenscad/examples/gists_csg/intersection_functional.py
pythonopenscad/examples/gists_csg/intersection_operator.py
pythonopenscad/examples/gists_csg/minkowski_example.py
pythonopenscad/examples/gists_csg/union_functional.py
pythonopenscad/examples/gists_csg/union_operator.py
pythonopenscad/examples/gists_other/__init__.py
pythonopenscad/examples/gists_other/global_variables_example.py
pythonopenscad/examples/gists_other/modifier_background_example.py
pythonopenscad/examples/gists_other/modifier_combinations_example.py
pythonopenscad/examples/gists_other/modifier_debug_example.py
pythonopenscad/examples/gists_other/modifier_disable_example.py
pythonopenscad/examples/gists_other/modifier_show_only_example.py
pythonopenscad/examples/gists_other/modules_example.py
pythonopenscad/examples/gists_other/render_example.py
pythonopenscad/examples/gists_other/snake_case_style_example.py
pythonopenscad-2.2.19.dist-info/METADATA
pythonopenscad-2.2.19.dist-info/WHEEL
pythonopenscad-2.2.19.dist-info/RECORD
