Metadata-Version: 2.4
Name: pythonopenscad
Version: 2.2.19
Summary: Yet Another Python OpenSCAD API. This is a thin wrapper for generating OpenSCAD 3D model scripts.
Project-URL: Homepage, https://github.com/owebeeone/pythonopenscad
Project-URL: Bug Tracker, https://github.com/owebeeone/pythonopenscad/issues
Author-email: Gianni Mariani <gianni@mariani.ws>
Classifier: License :: OSI Approved :: GNU Lesser General Public License v2 or later (LGPLv2+)
Classifier: Operating System :: OS Independent
Classifier: Programming Language :: Python :: 3
Requires-Python: >=3.10
Requires-Dist: anchorscad-linear>=0.1.1
Requires-Dist: datatrees>=0.2.1
Requires-Dist: distributed>=2025.1.0
Requires-Dist: fonttools>=4.57.0
Requires-Dist: frozendict>=2.3.0
Requires-Dist: hershey-fonts>=2.1.0
Requires-Dist: manifold3d>=3.1.0
Requires-Dist: mapbox-earcut>=1.0.3
Requires-Dist: mapbox>=0.18.1
Requires-Dist: numpy-stl>=3.2.0
Requires-Dist: numpy>=2.2.1
Requires-Dist: pillow>=11.0.0
Requires-Dist: pyglm>=2.8.0
Requires-Dist: pyopengl>=3.1.9
Requires-Dist: uharfbuzz>=0.48.0
